{
  "generator-jhipster": {
    "applicationType": "monolith",
    "gitCompany": "",
    "baseName": "ProductionPlan",
    "packageName": "com.abs.production.plan",
    "packageFolder": "com/abs/production/plan",
    "serverPort": 8080,
    "serviceDiscoveryType": false,
    "authenticationType": "jwt",
    "cacheProvider": "ehcache",
    "enableHibernateCache": false,
    "websocket": false,
    "databaseType": "sql",
    "devDatabaseType": "h2Disk",
    "prodDatabaseType": "mysql",
    "searchEngine": false,
    "enableSwaggerCodegen": false,
    "messageBroker": false,
    "buildTool": "maven",
    "useSass": true,
    "clientPackageManager": "npm",
    "testFrameworks": [],
    "enableTranslation": true,
    "nativeLanguage": "en",
    "languages": ["en", "ta"],
    "clientFramework": "react",
    "jhiPrefix": "jhi",
    "withAdminUi": true,
    "blueprints": [],
    "otherModules": [],
    "jhipsterVersion": "7.0.1",
    "skipClient": false,
    "skipServer": false,
    "skipUserManagement": false,
    "skipCheckLengthOfIdentifier": false,
    "skipFakeData": false,
    "entitySuffix": "",
    "dtoSuffix": "DTO",
    "pages": [],
    "creationTimestamp": 1617465914527,
    "jwtSecretKey": "OTIyMjY5ZTM1OTAzYWQxMzE0OWMzOWNkNDQ0YmJlY2MwZjg0ZGZmZTAyNGVhYzM5MmI2ZGY2MTYxNWIwMTdmNjIyZTZjMDljZDU2NDFiYTA0NTBjNDM3NDUzZTkzNGUzYWQ5MTk2YTVhMGJlMjMxNDNjYmZmMmU1NDhhMGQ3ZTk=",
    "clientTheme": "none",
    "clientThemeVariant": "",
    "reactive": false,
    "entities": ["Region", "Country", "Location", "Department", "Task", "Employee", "Job", "JobHistory"],
    "lastLiquibaseTimestamp": 1617631324000
  },
  "git-provider": "GitHub",
  "git-company": "spbbalaji",
  "repository-name": "abs-production-plan"
}
